okaeri_sdk/__init__.py
okaeri_sdk/client.py
okaeri_sdk/aicensor/__init__.py
okaeri_sdk/aicensor/aicensor.py
okaeri_sdk/aicensor/model/__init__.py
okaeri_sdk/aicensor/model/prediction_info.py
okaeri_sdk/noproxy/__init__.py
okaeri_sdk/noproxy/noproxy.py
okaeri_sdk/noproxy/model/__init__.py
okaeri_sdk/noproxy/model/address_info.py
okaeri_sdk-1.2.4.dist-info/LICENSE
okaeri_sdk-1.2.4.dist-info/METADATA
okaeri_sdk-1.2.4.dist-info/WHEEL
okaeri_sdk-1.2.4.dist-info/top_level.txt
okaeri_sdk-1.2.4.dist-info/RECORD
