Metadata-Version: 2.1
Name: okaeri-sdk
Version: 1.2.4
Summary: Okaeri Services SDK
Home-page: https://github.com/OkaeriPoland/okaeri-sdk-python
Author: Dawid Sawicki
Author-email: dawid@okaeri.eu
License: MIT
Platform: UNKNOWN
Classifier: Operating System :: OS Independent
Classifier: License :: OSI Approved :: MIT License
Classifier: Development Status :: 4 - Beta
Classifier: Programming Language :: Python :: 3.7
Classifier: Programming Language :: Python :: 3.8
Classifier: Programming Language :: Python :: 3.9
Classifier: Programming Language :: Python :: 3.10
Requires-Dist: requests
Requires-Dist: marshmallow-dataclass
